README.rst
setup.cfg
setup.py
unwiredlabs/__init__.py
unwiredlabs/network.py
unwiredlabs/request.py
unwiredlabs/response.py
unwiredlabs/version.py
unwiredlabs.egg-info/PKG-INFO
unwiredlabs.egg-info/SOURCES.txt
unwiredlabs.egg-info/dependency_links.txt
unwiredlabs.egg-info/requires.txt
unwiredlabs.egg-info/top_level.txt