Metadata-Version: 1.1
Name: unwiredlabs
Version: 0.3.0
Summary: Unwiredlabs Location API client.
Home-page: https://github.com/anfema/python-unwired
Author: Johannes Schriewer
Author-email: j.schriewer@anfe.ma
License: BSD License
Platform: UNKNOWN
Classifier: Intended Audience :: Developers
Classifier: License :: OSI Approved :: BSD License
Classifier: Operating System :: OS Independent
Classifier: Programming Language :: Python
Classifier: Programming Language :: Python :: 3.4
